nbdev_apl/__init__.py
nbdev_apl/_modidx.py
nbdev_apl/_nbdev.py
nbdev_apl-0.0.2368.dist-info/licenses/LICENSE
nbdev_apl-0.0.2368.dist-info/METADATA
nbdev_apl-0.0.2368.dist-info/WHEEL
nbdev_apl-0.0.2368.dist-info/entry_points.txt
nbdev_apl-0.0.2368.dist-info/top_level.txt
nbdev_apl-0.0.2368.dist-info/RECORD
